piwebx/__init__.py
piwebx/__version__.py
piwebx/af.py
piwebx/channels.py
piwebx/exceptions.py
piwebx/points.py
piwebx/servers.py
piwebx/streams.py
piwebx/types.py
piwebx/util/__init__.py
piwebx/util/data.py
piwebx/util/datastructures.py
piwebx/util/response.py
piwebx/util/time.py
piwebx-0.2.3.dist-info/METADATA
piwebx-0.2.3.dist-info/WHEEL
piwebx-0.2.3.dist-info/licenses/LICENSE
piwebx-0.2.3.dist-info/RECORD
