Metadata-Version: 2.4
Name: piwebx
Version: 0.2.3
Summary: Async data client for the AVEVA PI Web API
Project-URL: Homepage, https://github.com/hyprxa/piwebx
Project-URL: Source, https://github.com/hyprxa/piwebx
Author-email: Chris Newville <christopher.newville@hyprxa.io>
License-Expression: MIT
License-File: LICENSE
Classifier: Development Status :: 4 - Beta
Classifier: Intended Audience :: Developers
Classifier: License :: OSI Approved :: MIT License
Classifier: Operating System :: OS Independent
Classifier: Programming Language :: Python :: 3
Classifier: Programming Language :: Python :: 3 :: Only
Classifier: Programming Language :: Python :: 3.8
Classifier: Programming Language :: Python :: 3.9
Classifier: Programming Language :: Python :: 3.10
Classifier: Programming Language :: Python :: 3.11
Classifier: Programming Language :: Python :: 3.12
Classifier: Programming Language :: Python :: 3.13
Requires-Python: <4.0,>=3.8
Requires-Dist: dateparser<2.0.0,>=1.0.0
Requires-Dist: httpx-ws<1.0.0,>=0.6.0
Requires-Dist: httpx<1.0.0,>=0.25.0
Requires-Dist: orjson
Requires-Dist: pendulum<4.0.0,>=2.1.0
Requires-Dist: python-dateutil<3.0.0,>=2.7.0
Requires-Dist: typing-extensions
Provides-Extra: kerberos
Requires-Dist: httpx-kerberos<1.0.0,>=0.1.0; extra == 'kerberos'
